ezThread-0.0.1.dist-info/DESCRIPTION.rst
ezThread-0.0.1.dist-info/METADATA
ezThread-0.0.1.dist-info/RECORD
ezThread-0.0.1.dist-info/WHEEL
ezThread-0.0.1.dist-info/metadata.json
ezThread-0.0.1.dist-info/top_level.txt
ezthread/__init__.py
ezthread/ezthread.py
