Metadata-Version: 2.0
Name: ezThread
Version: 0.0.1
Summary: Threading in Python made ez
Home-page: https://github.com/Vilsol/ezThread
Author: Vilsol
Author-email: me@vil.so
License: UNKNOWN
Platform: UNKNOWN
